CHANGES.txt
CONTRIBUTORS.txt
LICENCE.txt
MANIFEST.in
README.rst
setup.py
src/inouk/__init__.py
src/inouk.edofx.egg-info/PKG-INFO
src/inouk.edofx.egg-info/SOURCES.txt
src/inouk.edofx.egg-info/dependency_links.txt
src/inouk.edofx.egg-info/namespace_packages.txt
src/inouk.edofx.egg-info/top_level.txt
src/inouk/edofx/__init__.py