Metadata-Version: 1.1
Name: inouk.edofx
Version: 0.3.9
Summary: A framework to read and write OFX files Version 1.
Home-page: https://github.com/cmorisse/inouk.edofx
Author: Cyril MORISSE
Author-email: cmorisse@boxes3.net
License: MIT
Keywords: ofx
Platform: UNKNOWN
Classifier: Development Status :: 4 - Beta
Classifier: Environment :: Console
Classifier: Intended Audience :: Developers
Classifier: Topic :: Text Processing :: Markup :: SGML
Classifier: License :: OSI Approved :: MIT License
Classifier: Programming Language :: Python
Classifier: Natural Language :: English
